{"type":"FeatureCollection","metadata":{"generated":1570602425000,"url":"https://earthquake.usgs.gov/earthquakes/feed/v1.0/summary/4.5_week.geojson","title":"USGS Magnitude 4.5+ Earthquakes, Past Week","status":200,"api":"1.8.1","count":78},"features":[{"type":"Feature","properties":{"mag":4.5999999999999996,"place":"108km NW of Turkmenbasy, Turkmenistan","time":1570590389555,"updated":1570592220040,"tz":180,"url":"https://earthquake.usgs.gov/earthquakes/eventpage/us70005sf8","detail":"https://earthquake.usgs.gov/earthquakes/feed/v1.0/detail/us70005sf8.geojson","felt":null,"cdi":null,"mmi":null,"alert":null,"status":"reviewed","tsunami":0,"sig":326,"net":"us","code":"70005sf8","ids":",us70005sf8,","sources":",us,","types":",geoserve,origin,phase-data,","nst":null,"dmin":5.585,"rms":1.0700000000000001,"gap":60,"magType":"mb","type":"earthquake","title":"M 4.6 - 108km NW of Turkmenbasy, Turkmenistan"},"geometry":{"type":"Point","coordinates":[52.024000000000001,40.689900000000002,10]},"id":"us70005sf8"},
{"type":"Feature","properties":{"mag":4.5,"place":"7km SSE of Shiroi, Japan","time":1570564710929,"updated":1570595439445,"tz":540,"url":"https://earthquake.usgs.gov/earthquakes/eventpage/us70005sbf","detail":"https://earthquake.usgs.gov/earthquakes/feed/v1.0/detail/us70005sbf.geojson","felt":32,"cdi":3.2000000000000002,"mmi":null,"alert":null,"status":"reviewed","tsunami":0,"sig":322,"net":"us","code":"70005sbf","ids":",us70005sbf,","sources":",us,","types":",dyfi,geoserve,origin,phase-data,","nst":null,"dmin":1.706,"rms":0.65000000000000002,"gap":135,"magType":"mb","type":"earthquake","title":"M 4.5 - 7km SSE of Shiroi, Japan"},"geometry":{"type":"Point","coordinates":[140.10810000000001,35.738399999999999,72.980000000000004]},"id":"us70005sbf"},
{"type":"Feature","properties":{"mag":4.5999999999999996,"place":"79km SE of Petropavlovsk-Kamchatskiy, Russia","time":1570561115278,"updated":1570562218040,"tz":660,"url":"https://earthquake.usgs.gov/earthquakes/eventpage/us70005s8f","detail":"https://earthquake.usgs.gov/earthquakes/feed/v1.0/detail/us70005s8f.geojson","felt":null,"cdi":null,"mmi":null,"alert":null,"status":"reviewed","tsunami":0,"sig":326,"net":"us","code":"70005s8f","ids":",us70005s8f,","sources":",us,","types":",geoserve,origin,phase-data,","nst":null,"dmin":0.70299999999999996,"rms":0.87,"gap":121,"magType":"mb","type":"earthquake","title":"M 4.6 - 79km SE of Petropavlovsk-Kamchatskiy, Russia"},"geometry":{"type":"Point","coordinates":[159.52160000000001,52.560499999999998,57.299999999999997]},"id":"us70005s8f"},
{"type":"Feature","properties":{"mag":4.5999999999999996,"place":"59km NNW of Dededo Village, Guam","time":1570544750912,"updated":1570547557040,"tz":600,"url":"https://earthquake.usgs.gov/earthquakes/eventpage/us70005rxr","detail":"https://earthquake.usgs.gov/earthquakes/feed/v1.0/detail/us70005rxr.geojson","felt":null,"cdi":null,"mmi":null,"alert":null,"status":"reviewed","tsunami":0,"sig":326,"net":"us","code":"70005rxr","ids":",us70005rxr,","sources":",us,","types":",geoserve,origin,phase-data,","nst":null,"dmin":0.48399999999999999,"rms":0.67000000000000004,"gap":77,"magType":"mb","type":"earthquake","title":"M 4.6 - 59km NNW of Dededo Village, Guam"},"geometry":{"type":"Point","coordinates":[144.6026,14.0015,182.84999999999999]},"id":"us70005rxr"},
{"type":"Feature","properties":{"mag":5,"place":"50km WNW of Kirakira, Solomon Islands","time":1570538737261,"updated":1570541808040,"tz":660,"url":"https://earthquake.usgs.gov/earthquakes/eventpage/us70005rx7","detail":"https://earthquake.usgs.gov/earthquakes/feed/v1.0/detail/us70005rx7.geojson","felt":null,"cdi":null,"mmi":null,"alert":null,"status":"reviewed","tsunami":0,"sig":385,"net":"us","code":"70005rx7","ids":",us70005rx7,","sources":",us,","types":",geoserve,origin,phase-data,","nst":null,"dmin":1.754,"rms":0.71999999999999997,"gap":30,"magType":"mb","type":"earthquake","title":"M 5.0 - 50km WNW of Kirakira, Solomon Islands"},"geometry":{"type":"Point","coordinates":[161.47810000000001,-10.341699999999999,53.189999999999998]},"id":"us70005rx7"},
{"type":"Feature","properties":{"mag":4.9000000000000004,"place":"19km NE of Putre, Chile","time":1570515484056,"updated":1570537537319,"tz":-240,"url":"https://earthquake.usgs.gov/earthquakes/eventpage/us70005rv1","detail":"https://earthquake.usgs.gov/earthquakes/feed/v1.0/detail/us70005rv1.geojson","felt":1,"cdi":2,"mmi":null,"alert":null,"status":"reviewed","tsunami":0,"sig":370,"net":"us","code":"70005rv1","ids":",us70005rv1,","sources":",us,","types":",dyfi,geoserve,origin,phase-data,","nst":null,"dmin":0.26300000000000001,"rms":1.4099999999999999,"gap":111,"magType":"mb","type":"earthquake","title":"M 4.9 - 19km NE of Putre, Chile"},"geometry":{"type":"Point","coordinates":[-69.421800000000005,-18.082999999999998,134.69]},"id":"us70005rv1"},
{"type":"Feature","properties":{"mag":4.9000000000000004,"place":"South Shetland Islands","time":1570511348152,"updated":1570512626040,"tz":null,"url":"https://earthquake.usgs.gov/earthquakes/eventpage/us70005run","detail":"https://earthquake.usgs.gov/earthquakes/feed/v1.0/detail/us70005run.geojson","felt":null,"cdi":null,"mmi":null,"alert":null,"status":"reviewed","tsunami":0,"sig":369,"net":"us","code":"70005run","ids":",us70005run,","sources":",us,","types":",origin,phase-data,","nst":null,"dmin":2.5619999999999998,"rms":1.28,"gap":83,"magType":"mb","type":"earthquake","title":"M 4.9 - South Shetland Islands"},"geometry":{"type":"Point","coordinates":[-53.881700000000002,-61.073799999999999,10]},"id":"us70005run"},
{"type":"Feature","properties":{"mag":4.5999999999999996,"place":"Reykjanes Ridge","time":1570509831661,"updated":1570512364040,"tz":-120,"url":"https://earthquake.usgs.gov/earthquakes/eventpage/us70005rus","detail":"https://earthquake.usgs.gov/earthquakes/feed/v1.0/detail/us70005rus.geojson","felt":null,"cdi":null,"mmi":null,"alert":null,"status":"reviewed","tsunami":0,"sig":326,"net":"us","code":"70005rus","ids":",us70005rus,","sources":",us,","types":",geoserve,origin,phase-data,","nst":null,"dmin":14.699999999999999,"rms":1.1399999999999999,"gap":92,"magType":"mb","type":"earthquake","title":"M 4.6 - Reykjanes Ridge"},"geometry":{"type":"Point","coordinates":[-35.164099999999998,54.331099999999999,10]},"id":"us70005rus"},
{"type":"Feature","properties":{"mag":4.5,"place":"10km NW of Culaman, Philippines","time":1570487842910,"updated":1570490712040,"tz":480,"url":"https://earthquake.usgs.gov/earthquakes/eventpage/us70005rsr","detail":"https://earthquake.usgs.gov/earthquakes/feed/v1.0/detail/us70005rsr.geojson","felt":null,"cdi":null,"mmi":null,"alert":null,"status":"reviewed","tsunami":0,"sig":312,"net":"us","code":"70005rsr","ids":",us70005rsr,","sources":",us,","types":",geoserve,origin,phase-data,","nst":null,"dmin":1.05,"rms":1.24,"gap":82,"magType":"mb","type":"earthquake","title":"M 4.5 - 10km NW of Culaman, Philippines"},"geometry":{"type":"Point","coordinates":[125.584,6.0122999999999998,10]},"id":"us70005rsr"},
{"type":"Feature","properties":{"mag":4.5,"place":"61km NNE of Meulaboh, Indonesia","time":1570482698544,"updated":1570487243040,"tz":420,"url":"https://earthquake.usgs.gov/earthquakes/eventpage/us70005rq1","detail":"https://earthquake.usgs.gov/earthquakes/feed/v1.0/detail/us70005rq1.geojson","felt":null,"cdi":null,"mmi":null,"alert":null,"status":"reviewed","tsunami":0,"sig":312,"net":"us","code":"70005rq1","ids":",us70005rq1,","sources":",us,","types":",geoserve,origin,phase-data,","nst":null,"dmin":0.80200000000000005,"rms":0.60999999999999999,"gap":135,"magType":"mb","type":"earthquake","title":"M 4.5 - 61km NNE of Meulaboh, Indonesia"},"geometry":{"type":"Point","coordinates":[96.438999999999993,4.6020000000000003,35.119999999999997]},"id":"us70005rq1"},
{"type":"Feature","properties":{"mag":5.0999999999999996,"place":"198km WSW of Kuripan, Indonesia","time":1570478971353,"updated":1570488081040,"tz":420,"url":"https://earthquake.usgs.gov/earthquakes/eventpage/us70005rnj","detail":"https://earthquake.usgs.gov/earthquakes/feed/v1.0/detail/us70005rnj.geojson","felt":null,"cdi":null,"mmi":null,"alert":null,"status":"reviewed","tsunami":1,"sig":400,"net":"us","code":"70005rnj","ids":",us70005rnj,","sources":",us,","types":",geoserve,moment-tensor,origin,phase-data,","nst":null,"dmin":1.7929999999999999,"rms":0.81000000000000005,"gap":49,"magType":"mww","type":"earthquake","title":"M 5.1 - 198km WSW of Kuripan, Indonesia"},"geometry":{"type":"Point","coordinates":[102.26609999999999,-6.0278,6.4000000000000004]},"id":"us70005rnj"},
{"type":"Feature","properties":{"mag":4.5999999999999996,"place":"83km N of Sikabaluan, Indonesia","time":1570473479006,"updated":1570482792040,"tz":420,"url":"https://earthquake.usgs.gov/earthquakes/eventpage/us70005rmk","detail":"https://earthquake.usgs.gov/earthquakes/feed/v1.0/detail/us70005rmk.geojson","felt":null,"cdi":null,"mmi":null,"alert":null,"status":"reviewed","tsunami":0,"sig":326,"net":"us","code":"70005rmk","ids":",us70005rmk,","sources":",us,","types":",geoserve,origin,phase-data,","nst":null,"dmin":2.1219999999999999,"rms":0.65000000000000002,"gap":87,"magType":"mb","type":"earthquake","title":"M 4.6 - 83km N of Sikabaluan, Indonesia"},"geometry":{"type":"Point","coordinates":[99.032899999999998,-0.36990000000000001,76.230000000000004]},"id":"us70005rmk"},
{"type":"Feature","properties":{"mag":4.5999999999999996,"place":"Prince Edward Islands region","time":1570461643969,"updated":1570466297040,"tz":180,"url":"https://earthquake.usgs.gov/earthquakes/eventpage/us70005rl8","detail":"https://earthquake.usgs.gov/earthquakes/feed/v1.0/detail/us70005rl8.geojson","felt":null,"cdi":null,"mmi":null,"alert":null,"status":"reviewed","tsunami":0,"sig":326,"net":"us","code":"70005rl8","ids":",us70005rl8,","sources":",us,","types":",geoserve,origin,phase-data,","nst":null,"dmin":14.597,"rms":0.92000000000000004,"gap":102,"magType":"mb","type":"earthquake","title":"M 4.6 - Prince Edward Islands region"},"geometry":{"type":"Point","coordinates":[38.883099999999999,-44.171399999999998,10]},"id":"us70005rl8"},
{"type":"Feature","properties":{"mag":4.7999999999999998,"place":"Western Indian-Antarctic Ridge","time":1570458132293,"updated":1570463111040,"tz":480,"url":"https://earthquake.usgs.gov/earthquakes/eventpage/us70005rkt","detail":"https://earthquake.usgs.gov/earthquakes/feed/v1.0/detail/us70005rkt.geojson","felt":null,"cdi":null,"mmi":null,"alert":null,"status":"reviewed","tsunami":0,"sig":354,"net":"us","code":"70005rkt","ids":",us70005rkt,","sources":",us,","types":",geoserve,origin,phase-data,","nst":null,"dmin":16.681000000000001,"rms":0.88,"gap":129,"magType":"mb","type":"earthquake","title":"M 4.8 - Western Indian-Antarctic Ridge"},"geometry":{"type":"Point","coordinates":[123.8094,-48.879399999999997,10]},"id":"us70005rkt"},
{"type":"Feature","properties":{"mag":4.7000000000000002,"place":"17km NNE of Mongar, Bhutan","time":1570451746503,"updated":1570480966581,"tz":360,"url":"https://earthquake.usgs.gov/earthquakes/eventpage/us70005rkb","detail":"https://earthquake.usgs.gov/earthquakes/feed/v1.0/detail/us70005rkb.geojson","felt":6,"cdi":4.2999999999999998,"mmi":null,"alert":null,"status":"reviewed","tsunami":0,"sig":342,"net":"us","code":"70005rkb","ids":",us70005rkb,","sources":",us,","types":",dyfi,geoserve,origin,phase-data,","nst":null,"dmin":8.4120000000000008,"rms":0.55000000000000004,"gap":155,"magType":"mb","type":"earthquake","title":"M 4.7 - 17km NNE of Mongar, Bhutan"},"geometry":{"type":"Point","coordinates":[91.331400000000002,27.404900000000001,10]},"id":"us70005rkb"},
{"type":"Feature","properties":{"mag":4.9000000000000004,"place":"27km S of Pagan, Northern Mariana Islands","time":1570439034507,"updated":1570442779040,"tz":600,"url":"https://earthquake.usgs.gov/earthquakes/eventpage/us70005rj9","detail":"https://earthquake.usgs.gov/earthquakes/feed/v1.0/detail/us70005rj9.geojson","felt":null,"cdi":null,"mmi":null,"alert":null,"status":"reviewed","tsunami":0,"sig":369,"net":"us","code":"70005rj9","ids":",us70005rj9,","sources":",us,","types":",geoserve,origin,phase-data,","nst":null,"dmin":2.6110000000000002,"rms":1.1799999999999999,"gap":96,"magType":"mb","type":"earthquake","title":"M 4.9 - 27km S of Pagan, Northern Mariana Islands"},"geometry":{"type":"Point","coordinates":[145.7764,17.866800000000001,182.12]},"id":"us70005rj9"},
{"type":"Feature","properties":{"mag":4.5999999999999996,"place":"3km WNW of Marcellinara, Italy","time":1570428693884,"updated":1570519182496,"tz":60,"url":"https://earthquake.usgs.gov/earthquakes/eventpage/us70005rig","detail":"https://earthquake.usgs.gov/earthquakes/feed/v1.0/detail/us70005rig.geojson","felt":1,"cdi":5.5,"mmi":null,"alert":null,"status":"reviewed","tsunami":0,"sig":326,"net":"us","code":"70005rig","ids":",us70005rig,","sources":",us,","types":",dyfi,geoserve,origin,phase-data,","nst":null,"dmin":0.34499999999999997,"rms":1.01,"gap":55,"magType":"mb","type":"earthquake","title":"M 4.6 - 3km WNW of Marcellinara, Italy"},"geometry":{"type":"Point","coordinates":[16.4466,38.933500000000002,35]},"id":"us70005rig"},
{"type":"Feature","properties":{"mag":4.7999999999999998,"place":"94km W of El Aguilar, Argentina","time":1570423846874,"updated":1570425045040,"tz":-180,"url":"https://earthquake.usgs.gov/earthquakes/eventpage/us70005ric","detail":"https://earthquake.usgs.gov/earthquakes/feed/v1.0/detail/us70005ric.geojson","felt":null,"cdi":null,"mmi":null,"alert":null,"status":"reviewed","tsunami":0,"sig":354,"net":"us","code":"70005ric","ids":",us70005ric,","sources":",us,","types":",geoserve,origin,phase-data,","nst":null,"dmin":1.4570000000000001,"rms":0.90000000000000002,"gap":51,"magType":"mb","type":"earthquake","title":"M 4.8 - 94km W of El Aguilar, Argentina"},"geometry":{"type":"Point","coordinates":[-66.605800000000002,-23.111599999999999,198.55000000000001]},"id":"us70005ric"},
{"type":"Feature","properties":{"mag":4.7000000000000002,"place":"53km SSE of Isangel, Vanuatu","time":1570420007962,"updated":1570423733040,"tz":660,"url":"https://earthquake.usgs.gov/earthquakes/eventpage/us70005rhy","detail":"https://earthquake.usgs.gov/earthquakes/feed/v1.0/detail/us70005rhy.geojson","felt":null,"cdi":null,"mmi":null,"alert":null,"status":"reviewed","tsunami":0,"sig":340,"net":"us","code":"70005rhy","ids":",us70005rhy,","sources":",us,","types":",geoserve,origin,phase-data,","nst":null,"dmin":3.2120000000000002,"rms":1.0900000000000001,"gap":111,"magType":"mb","type":"earthquake","title":"M 4.7 - 53km SSE of Isangel, Vanuatu"},"geometry":{"type":"Point","coordinates":[169.4605,-19.9941,113.52]},"id":"us70005rhy"},
{"type":"Feature","properties":{"mag":4.9000000000000004,"place":"20km S of Opotiki, New Zealand","time":1570418987310,"updated":1570422835166,"tz":720,"url":"https://earthquake.usgs.gov/earthquakes/eventpage/us70005rhr","detail":"https://earthquake.usgs.gov/earthquakes/feed/v1.0/detail/us70005rhr.geojson","felt":13,"cdi":3.3999999999999999,"mmi":null,"alert":null,"status":"reviewed","tsunami":0,"sig":374,"net":"us","code":"70005rhr","ids":",us70005rhr,","sources":",us,","types":",dyfi,geoserve,origin,phase-data,","nst":null,"dmin":0.41099999999999998,"rms":1.1699999999999999,"gap":78,"magType":"mww","type":"earthquake","title":"M 4.9 - 20km S of Opotiki, New Zealand"},"geometry":{"type":"Point","coordinates":[177.25360000000001,-38.263199999999998,35]},"id":"us70005rhr"},
{"type":"Feature","properties":{"mag":4.5999999999999996,"place":"131km N of Road Town, British Virgin Islands","time":1570410134234,"updated":1570439096850,"tz":-240,"url":"https://earthquake.usgs.gov/earthquakes/eventpage/us70005rgt","detail":"https://earthquake.usgs.gov/earthquakes/feed/v1.0/detail/us70005rgt.geojson","felt":2,"cdi":3.7999999999999998,"mmi":null,"alert":null,"status":"reviewed","tsunami":0,"sig":326,"net":"us","code":"70005rgt","ids":",pt19280050,us70005rgt,","sources":",pt,us,","types":",dyfi,geoserve,origin,phase-data,","nst":null,"dmin":1.9159999999999999,"rms":0.90000000000000002,"gap":127,"magType":"mb","type":"earthquake","title":"M 4.6 - 131km N of Road Town, British Virgin Islands"},"geometry":{"type":"Point","coordinates":[-64.521500000000003,19.597200000000001,10]},"id":"us70005rgt"},
{"type":"Feature","properties":{"mag":5.2999999999999998,"place":"84km S of Bristol Island, South Sandwich Islands","time":1570407418485,"updated":1570413300040,"tz":-120,"url":"https://earthquake.usgs.gov/earthquakes/eventpage/us70005rgp","detail":"https://earthquake.usgs.gov/earthquakes/feed/v1.0/detail/us70005rgp.geojson","felt":null,"cdi":null,"mmi":null,"alert":null,"status":"reviewed","tsunami":0,"sig":432,"net":"us","code":"70005rgp","ids":",us70005rgp,","sources":",us,","types":",geoserve,origin,phase-data,","nst":null,"dmin":7.8360000000000003,"rms":0.79000000000000004,"gap":37,"magType":"mb","type":"earthquake","title":"M 5.3 - 84km S of Bristol Island, South Sandwich Islands"},"geometry":{"type":"Point","coordinates":[-26.263500000000001,-59.784199999999998,35]},"id":"us70005rgp"},
{"type":"Feature","properties":{"mag":4.5999999999999996,"place":"21km SE of Yanai, Japan","time":1570402951426,"updated":1570493266071,"tz":540,"url":"https://earthquake.usgs.gov/earthquakes/eventpage/us70005rfp","detail":"https://earthquake.usgs.gov/earthquakes/feed/v1.0/detail/us70005rfp.geojson","felt":13,"cdi":3.1000000000000001,"mmi":null,"alert":null,"status":"reviewed","tsunami":0,"sig":330,"net":"us","code":"70005rfp","ids":",us70005rfp,","sources":",us,","types":",dyfi,geoserve,origin,phase-data,","nst":null,"dmin":1.341,"rms":0.63,"gap":64,"magType":"mb","type":"earthquake","title":"M 4.6 - 21km SE of Yanai, Japan"},"geometry":{"type":"Point","coordinates":[132.26900000000001,33.814900000000002,50.170000000000002]},"id":"us70005rfp"},
{"type":"Feature","properties":{"mag":4.7000000000000002,"place":"12km NNE of Farallon de Pajaros, Northern Mariana Islands","time":1570396860867,"updated":1570397790040,"tz":600,"url":"https://earthquake.usgs.gov/earthquakes/eventpage/us70005rf2","detail":"https://earthquake.usgs.gov/earthquakes/feed/v1.0/detail/us70005rf2.geojson","felt":null,"cdi":null,"mmi":null,"alert":null,"status":"reviewed","tsunami":0,"sig":340,"net":"us","code":"70005rf2","ids":",us70005rf2,","sources":",us,","types":",geoserve,origin,phase-data,","nst":null,"dmin":5.4299999999999997,"rms":0.64000000000000001,"gap":144,"magType":"mb","type":"earthquake","title":"M 4.7 - 12km NNE of Farallon de Pajaros, Northern Mariana Islands"},"geometry":{"type":"Point","coordinates":[144.9436,20.640499999999999,119.94]},"id":"us70005rf2"},
{"type":"Feature","properties":{"mag":4.9000000000000004,"place":"146km W of Merizo Village, Guam","time":1570383646029,"updated":1570393201779,"tz":600,"url":"https://earthquake.usgs.gov/earthquakes/eventpage/us70005rd5","detail":"https://earthquake.usgs.gov/earthquakes/feed/v1.0/detail/us70005rd5.geojson","felt":1,"cdi":1,"mmi":null,"alert":null,"status":"reviewed","tsunami":0,"sig":369,"net":"us","code":"70005rd5","ids":",us70005rd5,","sources":",us,","types":",dyfi,geoserve,origin,phase-data,","nst":null,"dmin":1.5760000000000001,"rms":0.78000000000000003,"gap":72,"magType":"mb","type":"earthquake","title":"M 4.9 - 146km W of Merizo Village, Guam"},"geometry":{"type":"Point","coordinates":[143.3253,13.107699999999999,206.83000000000001]},"id":"us70005rd5"},
{"type":"Feature","properties":{"mag":5,"place":"19km SE of Bristol Island, South Sandwich Islands","time":1570382020048,"updated":1570383167040,"tz":-120,"url":"https://earthquake.usgs.gov/earthquakes/eventpage/us70005rcr","detail":"https://earthquake.usgs.gov/earthquakes/feed/v1.0/detail/us70005rcr.geojson","felt":null,"cdi":null,"mmi":null,"alert":null,"status":"reviewed","tsunami":0,"sig":385,"net":"us","code":"70005rcr","ids":",us70005rcr,","sources":",us,","types":",geoserve,origin,phase-data,","nst":null,"dmin":7.4409999999999998,"rms":0.56999999999999995,"gap":83,"magType":"mb","type":"earthquake","title":"M 5.0 - 19km SE of Bristol Island, South Sandwich Islands"},"geometry":{"type":"Point","coordinates":[-26.2563,-59.144500000000001,130.28]},"id":"us70005rcr"},
{"type":"Feature","properties":{"mag":4.5999999999999996,"place":"81km WNW of Kota Ternate, Indonesia","time":1570377034749,"updated":1570378212040,"tz":480,"url":"https://earthquake.usgs.gov/earthquakes/eventpage/us70005rc7","detail":"https://earthquake.usgs.gov/earthquakes/feed/v1.0/detail/us70005rc7.geojson","felt":null,"cdi":null,"mmi":null,"alert":null,"status":"reviewed","tsunami":0,"sig":326,"net":"us","code":"70005rc7","ids":",us70005rc7,","sources":",us,","types":",geoserve,origin,phase-data,","nst":null,"dmin":0.73199999999999998,"rms":0.57999999999999996,"gap":80,"magType":"mb","type":"earthquake","title":"M 4.6 - 81km WNW of Kota Ternate, Indonesia"},"geometry":{"type":"Point","coordinates":[126.6651,0.98340000000000005,46.159999999999997]},"id":"us70005rc7"},
{"type":"Feature","properties":{"mag":4.96,"place":"113km N of Road Town, British Virgin Islands","time":1570374644220,"updated":1570409742851,"tz":-240,"url":"https://earthquake.usgs.gov/earthquakes/eventpage/pr2019279014","detail":"https://earthquake.usgs.gov/earthquakes/feed/v1.0/detail/pr2019279014.geojson","felt":6,"cdi":2.7000000000000002,"mmi":null,"alert":null,"status":"reviewed","tsunami":0,"sig":380,"net":"pr","code":"2019279014","ids":",pt19279050,us70005rbn,pr2019279014,","sources":",pt,us,pr,","types":",dyfi,geoserve,origin,phase-data,","nst":29,"dmin":2.0566,"rms":0.44,"gap":228,"magType":"md","type":"earthquake","title":"M 5.0 - 113km N of Road Town, British Virgin Islands"},"geometry":{"type":"Point","coordinates":[-64.5655,19.6966,15]},"id":"pr2019279014"},
{"type":"Feature","properties":{"mag":5.9000000000000004,"place":"73km NNE of Calama, Chile","time":1570358455830,"updated":1570462180040,"tz":-240,"url":"https://earthquake.usgs.gov/earthquakes/eventpage/us70005r9l","detail":"https://earthquake.usgs.gov/earthquakes/feed/v1.0/detail/us70005r9l.geojson","felt":16,"cdi":5.4000000000000004,"mmi":4.1500000000000004,"alert":"green","status":"reviewed","tsunami":0,"sig":544,"net":"us","code":"70005r9l","ids":",us70005r9l,","sources":",us,","types":",dyfi,geoserve,losspager,moment-tensor,origin,phase-data,shakemap,","nst":null,"dmin":0.63500000000000001,"rms":1.02,"gap":67,"magType":"mww","type":"earthquake","title":"M 5.9 - 73km NNE of Calama, Chile"},"geometry":{"type":"Point","coordinates":[-68.567700000000002,-21.901700000000002,112.38]},"id":"us70005r9l"},
{"type":"Feature","properties":{"mag":4.5999999999999996,"place":"91km E of Namie, Japan","time":1570341795505,"updated":1570347230653,"tz":540,"url":"https://earthquake.usgs.gov/earthquakes/eventpage/us70005r81","detail":"https://earthquake.usgs.gov/earthquakes/feed/v1.0/detail/us70005r81.geojson","felt":1,"cdi":1,"mmi":null,"alert":null,"status":"reviewed","tsunami":0,"sig":326,"net":"us","code":"70005r81","ids":",us70005r81,","sources":",us,","types":",dyfi,geoserve,origin,phase-data,","nst":null,"dmin":1.087,"rms":0.63,"gap":146,"magType":"mb","type":"earthquake","title":"M 4.6 - 91km E of Namie, Japan"},"geometry":{"type":"Point","coordinates":[142.02889999999999,37.4039,34.890000000000001]},"id":"us70005r81"},
{"type":"Feature","properties":{"mag":4.9000000000000004,"place":"141km WSW of Naze, Japan","time":1570307544793,"updated":1570570425415,"tz":540,"url":"https://earthquake.usgs.gov/earthquakes/eventpage/us70005r5h","detail":"https://earthquake.usgs.gov/earthquakes/feed/v1.0/detail/us70005r5h.geojson","felt":2,"cdi":3.7999999999999998,"mmi":null,"alert":null,"status":"reviewed","tsunami":0,"sig":370,"net":"us","code":"70005r5h","ids":",us70005r5h,","sources":",us,","types":",dyfi,geoserve,origin,phase-data,","nst":null,"dmin":1.048,"rms":1.21,"gap":75,"magType":"mww","type":"earthquake","title":"M 4.9 - 141km WSW of Naze, Japan"},"geometry":{"type":"Point","coordinates":[128.15309999999999,27.883400000000002,39.670000000000002]},"id":"us70005r5h"},
{"type":"Feature","properties":{"mag":4.5,"place":"128km WSW of Naze, Japan","time":1570307104659,"updated":1570598481040,"tz":540,"url":"https://earthquake.usgs.gov/earthquakes/eventpage/us70005r5f","detail":"https://earthquake.usgs.gov/earthquakes/feed/v1.0/detail/us70005r5f.geojson","felt":null,"cdi":null,"mmi":null,"alert":null,"status":"reviewed","tsunami":0,"sig":312,"net":"us","code":"70005r5f","ids":",us70005r5f,","sources":",us,","types":",geoserve,origin,phase-data,","nst":null,"dmin":1.0589999999999999,"rms":1.0900000000000001,"gap":81,"magType":"mb","type":"earthquake","title":"M 4.5 - 128km WSW of Naze, Japan"},"geometry":{"type":"Point","coordinates":[128.28569999999999,27.899100000000001,10]},"id":"us70005r5f"},
{"type":"Feature","properties":{"mag":4.9000000000000004,"place":"134km WSW of Naze, Japan","time":1570306699770,"updated":1570307575040,"tz":540,"url":"https://earthquake.usgs.gov/earthquakes/eventpage/us70005r59","detail":"https://earthquake.usgs.gov/earthquakes/feed/v1.0/detail/us70005r59.geojson","felt":null,"cdi":null,"mmi":null,"alert":null,"status":"reviewed","tsunami":0,"sig":369,"net":"us","code":"70005r59","ids":",us70005r59,","sources":",us,","types":",geoserve,origin,phase-data,","nst":null,"dmin":1.1759999999999999,"rms":1.27,"gap":64,"magType":"mb","type":"earthquake","title":"M 4.9 - 134km WSW of Naze, Japan"},"geometry":{"type":"Point","coordinates":[128.17599999999999,28.014199999999999,16.539999999999999]},"id":"us70005r59"},
{"type":"Feature","properties":{"mag":4.5999999999999996,"place":"125km SSE of Hachijo-jima, Japan","time":1570303672883,"updated":1570596909040,"tz":540,"url":"https://earthquake.usgs.gov/earthquakes/eventpage/us70005r4z","detail":"https://earthquake.usgs.gov/earthquakes/feed/v1.0/detail/us70005r4z.geojson","felt":null,"cdi":null,"mmi":null,"alert":null,"status":"reviewed","tsunami":0,"sig":326,"net":"us","code":"70005r4z","ids":",us70005r4z,","sources":",us,","types":",geoserve,origin,phase-data,","nst":null,"dmin":1.149,"rms":0.66000000000000003,"gap":124,"magType":"mb","type":"earthquake","title":"M 4.6 - 125km SSE of Hachijo-jima, Japan"},"geometry":{"type":"Point","coordinates":[140.3546,32.057000000000002,77.629999999999995]},"id":"us70005r4z"},
{"type":"Feature","properties":{"mag":4.5999999999999996,"place":"86km SSE of Pondaguitan, Philippines","time":1570295468088,"updated":1570549870040,"tz":480,"url":"https://earthquake.usgs.gov/earthquakes/eventpage/us70005r4c","detail":"https://earthquake.usgs.gov/earthquakes/feed/v1.0/detail/us70005r4c.geojson","felt":null,"cdi":null,"mmi":null,"alert":null,"status":"reviewed","tsunami":0,"sig":326,"net":"us","code":"70005r4c","ids":",us70005r4c,","sources":",us,","types":",geoserve,origin,phase-data,","nst":null,"dmin":1.6839999999999999,"rms":0.82999999999999996,"gap":92,"magType":"mb","type":"earthquake","title":"M 4.6 - 86km SSE of Pondaguitan, Philippines"},"geometry":{"type":"Point","coordinates":[126.5312,5.6665000000000001,75.799999999999997]},"id":"us70005r4c"},
{"type":"Feature","properties":{"mag":5,"place":"Reykjanes Ridge","time":1570294900409,"updated":1570548202040,"tz":-120,"url":"https://earthquake.usgs.gov/earthquakes/eventpage/us70005r46","detail":"https://earthquake.usgs.gov/earthquakes/feed/v1.0/detail/us70005r46.geojson","felt":null,"cdi":null,"mmi":null,"alert":null,"status":"reviewed","tsunami":0,"sig":385,"net":"us","code":"70005r46","ids":",us70005r46,","sources":",us,","types":",geoserve,origin,phase-data,","nst":null,"dmin":6.3730000000000002,"rms":0.72999999999999998,"gap":40,"magType":"mww","type":"earthquake","title":"M 5.0 - Reykjanes Ridge"},"geometry":{"type":"Point","coordinates":[-30.0547,59.853200000000001,10]},"id":"us70005r46"},
{"type":"Feature","properties":{"mag":4.9000000000000004,"place":"23km NW of San Marcos, Mexico","time":1570292411132,"updated":1570338653679,"tz":-360,"url":"https://earthquake.usgs.gov/earthquakes/eventpage/us70005r3t","detail":"https://earthquake.usgs.gov/earthquakes/feed/v1.0/detail/us70005r3t.geojson","felt":19,"cdi":4.7999999999999998,"mmi":null,"alert":null,"status":"reviewed","tsunami":0,"sig":379,"net":"us","code":"70005r3t","ids":",us70005r3t,","sources":",us,","types":",dyfi,geoserve,origin,phase-data,","nst":null,"dmin":1.1100000000000001,"rms":0.95999999999999996,"gap":167,"magType":"mb","type":"earthquake","title":"M 4.9 - 23km NW of San Marcos, Mexico"},"geometry":{"type":"Point","coordinates":[-99.523200000000003,16.929400000000001,17.329999999999998]},"id":"us70005r3t"},
{"type":"Feature","properties":{"mag":4.5,"place":"13km S of Lardos, Greece","time":1570287098030,"updated":1570313141766,"tz":120,"url":"https://earthquake.usgs.gov/earthquakes/eventpage/us70005r33","detail":"https://earthquake.usgs.gov/earthquakes/feed/v1.0/detail/us70005r33.geojson","felt":15,"cdi":3.1000000000000001,"mmi":null,"alert":null,"status":"reviewed","tsunami":0,"sig":316,"net":"us","code":"70005r33","ids":",us70005r33,","sources":",us,","types":",dyfi,geoserve,origin,phase-data,","nst":null,"dmin":0.25800000000000001,"rms":0.41999999999999998,"gap":131,"magType":"mb","type":"earthquake","title":"M 4.5 - 13km S of Lardos, Greece"},"geometry":{"type":"Point","coordinates":[28.012,35.970100000000002,74.950000000000003]},"id":"us70005r33"},
{"type":"Feature","properties":{"mag":5.0999999999999996,"place":"29km NNW of Finschhafen, Papua New Guinea","time":1570285729577,"updated":1570286653040,"tz":600,"url":"https://earthquake.usgs.gov/earthquakes/eventpage/us70005r30","detail":"https://earthquake.usgs.gov/earthquakes/feed/v1.0/detail/us70005r30.geojson","felt":null,"cdi":null,"mmi":null,"alert":null,"status":"reviewed","tsunami":1,"sig":400,"net":"us","code":"70005r30","ids":",us70005r30,","sources":",us,","types":",geoserve,origin,phase-data,","nst":null,"dmin":3.0539999999999998,"rms":0.84999999999999998,"gap":41,"magType":"mww","type":"earthquake","title":"M 5.1 - 29km NNW of Finschhafen, Papua New Guinea"},"geometry":{"type":"Point","coordinates":[147.72389999999999,-6.3821000000000003,73.019999999999996]},"id":"us70005r30"},
{"type":"Feature","properties":{"mag":4.9000000000000004,"place":"206km NW of Saumlaki, Indonesia","time":1570282391931,"updated":1570283311040,"tz":540,"url":"https://earthquake.usgs.gov/earthquakes/eventpage/us70005r2t","detail":"https://earthquake.usgs.gov/earthquakes/feed/v1.0/detail/us70005r2t.geojson","felt":null,"cdi":null,"mmi":null,"alert":null,"status":"reviewed","tsunami":0,"sig":369,"net":"us","code":"70005r2t","ids":",us70005r2t,","sources":",us,","types":",geoserve,origin,phase-data,","nst":null,"dmin":1.863,"rms":0.55000000000000004,"gap":100,"magType":"mb","type":"earthquake","title":"M 4.9 - 206km NW of Saumlaki, Indonesia"},"geometry":{"type":"Point","coordinates":[129.9101,-6.7187000000000001,152.06]},"id":"us70005r2t"},
{"type":"Feature","properties":{"mag":4.7000000000000002,"place":"21km WNW of Agat Village, Guam","time":1570275600953,"updated":1570452055786,"tz":600,"url":"https://earthquake.usgs.gov/earthquakes/eventpage/us70005r2h","detail":"https://earthquake.usgs.gov/earthquakes/feed/v1.0/detail/us70005r2h.geojson","felt":10,"cdi":3.3999999999999999,"mmi":null,"alert":null,"status":"reviewed","tsunami":0,"sig":343,"net":"us","code":"70005r2h","ids":",us70005r2h,","sources":",us,","types":",dyfi,geoserve,origin,phase-data,","nst":null,"dmin":0.41699999999999998,"rms":0.71999999999999997,"gap":79,"magType":"mb","type":"earthquake","title":"M 4.7 - 21km WNW of Agat Village, Guam"},"geometry":{"type":"Point","coordinates":[144.46770000000001,13.4384,143]},"id":"us70005r2h"},
{"type":"Feature","properties":{"mag":4.7000000000000002,"place":"78km NNW of Sola, Vanuatu","time":1570255852447,"updated":1570259940040,"tz":660,"url":"https://earthquake.usgs.gov/earthquakes/eventpage/us70005r0n","detail":"https://earthquake.usgs.gov/earthquakes/feed/v1.0/detail/us70005r0n.geojson","felt":null,"cdi":null,"mmi":null,"alert":null,"status":"reviewed","tsunami":0,"sig":340,"net":"us","code":"70005r0n","ids":",us70005r0n,","sources":",us,","types":",geoserve,origin,phase-data,","nst":null,"dmin":2.1909999999999998,"rms":0.66000000000000003,"gap":144,"magType":"mb","type":"earthquake","title":"M 4.7 - 78km NNW of Sola, Vanuatu"},"geometry":{"type":"Point","coordinates":[167.23390000000001,-13.2432,199.02000000000001]},"id":"us70005r0n"},
{"type":"Feature","properties":{"mag":4.5999999999999996,"place":"47km W of Dobo, Indonesia","time":1570253247542,"updated":1570258156040,"tz":540,"url":"https://earthquake.usgs.gov/earthquakes/eventpage/us70005r0j","detail":"https://earthquake.usgs.gov/earthquakes/feed/v1.0/detail/us70005r0j.geojson","felt":null,"cdi":null,"mmi":null,"alert":null,"status":"reviewed","tsunami":0,"sig":326,"net":"us","code":"70005r0j","ids":",us70005r0j,","sources":",us,","types":",geoserve,origin,phase-data,","nst":null,"dmin":3.2069999999999999,"rms":0.70999999999999996,"gap":54,"magType":"mb","type":"earthquake","title":"M 4.6 - 47km W of Dobo, Indonesia"},"geometry":{"type":"Point","coordinates":[133.78739999999999,-5.7553000000000001,10]},"id":"us70005r0j"},
{"type":"Feature","properties":{"mag":5,"place":"29km WNW of Little Sitkin Island, Alaska","time":1570247296004,"updated":1570276255584,"tz":-600,"url":"https://earthquake.usgs.gov/earthquakes/eventpage/us70005qzz","detail":"https://earthquake.usgs.gov/earthquakes/feed/v1.0/detail/us70005qzz.geojson","felt":null,"cdi":null,"mmi":null,"alert":null,"status":"reviewed","tsunami":0,"sig":385,"net":"us","code":"70005qzz","ids":",ak019crth3ku,us70005qzz,","sources":",ak,us,","types":",geoserve,origin,phase-data,","nst":null,"dmin":0.26300000000000001,"rms":0.94999999999999996,"gap":80,"magType":"mww","type":"earthquake","title":"M 5.0 - 29km WNW of Little Sitkin Island, Alaska"},"geometry":{"type":"Point","coordinates":[178.1003,52.028399999999998,132.86000000000001]},"id":"us70005qzz"},
{"type":"Feature","properties":{"mag":4.7000000000000002,"place":"Fiji region","time":1570235930168,"updated":1570239655040,"tz":-720,"url":"https://earthquake.usgs.gov/earthquakes/eventpage/us70005qzd","detail":"https://earthquake.usgs.gov/earthquakes/feed/v1.0/detail/us70005qzd.geojson","felt":null,"cdi":null,"mmi":null,"alert":null,"status":"reviewed","tsunami":0,"sig":340,"net":"us","code":"70005qzd","ids":",us70005qzd,","sources":",us,","types":",geoserve,origin,phase-data,","nst":null,"dmin":3.698,"rms":1.1699999999999999,"gap":86,"magType":"mb","type":"earthquake","title":"M 4.7 - Fiji region"},"geometry":{"type":"Point","coordinates":[-177.86789999999999,-18.019200000000001,571.71000000000004]},"id":"us70005qzd"},
{"type":"Feature","properties":{"mag":4.9000000000000004,"place":"29km WNW of Panguna, Papua New Guinea","time":1570208629759,"updated":1570287000040,"tz":660,"url":"https://earthquake.usgs.gov/earthquakes/eventpage/us70005qsj","detail":"https://earthquake.usgs.gov/earthquakes/feed/v1.0/detail/us70005qsj.geojson","felt":null,"cdi":null,"mmi":null,"alert":null,"status":"reviewed","tsunami":0,"sig":369,"net":"us","code":"70005qsj","ids":",us70005qsj,","sources":",us,","types":",geoserve,origin,phase-data,","nst":null,"dmin":3.6619999999999999,"rms":0.57999999999999996,"gap":78,"magType":"mb","type":"earthquake","title":"M 4.9 - 29km WNW of Panguna, Papua New Guinea"},"geometry":{"type":"Point","coordinates":[155.2312,-6.2244999999999999,160.34]},"id":"us70005qsj"},
{"type":"Feature","properties":{"mag":5,"place":"63km NNW of Dobo, Indonesia","time":1570195170712,"updated":1570196143040,"tz":540,"url":"https://earthquake.usgs.gov/earthquakes/eventpage/us70005qnt","detail":"https://earthquake.usgs.gov/earthquakes/feed/v1.0/detail/us70005qnt.geojson","felt":null,"cdi":null,"mmi":null,"alert":null,"status":"reviewed","tsunami":1,"sig":385,"net":"us","code":"70005qnt","ids":",us70005qnt,","sources":",us,","types":",geoserve,origin,phase-data,","nst":null,"dmin":2.8719999999999999,"rms":1.1699999999999999,"gap":90,"magType":"mb","type":"earthquake","title":"M 5.0 - 63km NNW of Dobo, Indonesia"},"geometry":{"type":"Point","coordinates":[133.92699999999999,-5.2689000000000004,41.810000000000002]},"id":"us70005qnt"},
{"type":"Feature","properties":{"mag":5,"place":"71km WNW of Talkeetna, Alaska","time":1570192083205,"updated":1570538292705,"tz":-540,"url":"https://earthquake.usgs.gov/earthquakes/eventpage/ak019cqb6c9o","detail":"https://earthquake.usgs.gov/earthquakes/feed/v1.0/detail/ak019cqb6c9o.geojson","felt":589,"cdi":4.9000000000000004,"mmi":3.7400000000000002,"alert":"green","status":"reviewed","tsunami":1,"sig":673,"net":"ak","code":"019cqb6c9o","ids":",at00pyunyq,ak019cqb6c9o,us70005qnc,","sources":",at,ak,us,","types":",dyfi,geoserve,ground-failure,impact-link,losspager,moment-tensor,oaf,origin,phase-data,shakemap,","nst":null,"dmin":null,"rms":0.58999999999999997,"gap":null,"magType":"mww","type":"earthquake","title":"M 5.0 - 71km WNW of Talkeetna, Alaska"},"geometry":{"type":"Point","coordinates":[-151.52000000000001,62.478400000000001,90.700000000000003]},"id":"ak019cqb6c9o"},
{"type":"Feature","properties":{"mag":4.7999999999999998,"place":"Scotia Sea","time":1570169652618,"updated":1570172584040,"tz":null,"url":"https://earthquake.usgs.gov/earthquakes/eventpage/us70005ql3","detail":"https://earthquake.usgs.gov/earthquakes/feed/v1.0/detail/us70005ql3.geojson","felt":null,"cdi":null,"mmi":null,"alert":null,"status":"reviewed","tsunami":0,"sig":354,"net":"us","code":"70005ql3","ids":",us70005ql3,","sources":",us,","types":",origin,phase-data,","nst":null,"dmin":6.9359999999999999,"rms":0.81000000000000005,"gap":65,"magType":"mb","type":"earthquake","title":"M 4.8 - Scotia Sea"},"geometry":{"type":"Point","coordinates":[-39.0505,-61.063600000000001,10]},"id":"us70005ql3"},
{"type":"Feature","properties":{"mag":4.9000000000000004,"place":"93km W of Arica, Chile","time":1570161746380,"updated":1570164254593,"tz":-300,"url":"https://earthquake.usgs.gov/earthquakes/eventpage/us70005qk0","detail":"https://earthquake.usgs.gov/earthquakes/feed/v1.0/detail/us70005qk0.geojson","felt":1,"cdi":3.3999999999999999,"mmi":null,"alert":null,"status":"reviewed","tsunami":0,"sig":370,"net":"us","code":"70005qk0","ids":",us70005qk0,","sources":",us,","types":",dyfi,geoserve,origin,phase-data,","nst":null,"dmin":1.6060000000000001,"rms":1.1200000000000001,"gap":146,"magType":"mww","type":"earthquake","title":"M 4.9 - 93km W of Arica, Chile"},"geometry":{"type":"Point","coordinates":[-71.173199999999994,-18.6252,17.739999999999998]},"id":"us70005qk0"},
{"type":"Feature","properties":{"mag":4.5,"place":"141km WNW of Coquimbo, Chile","time":1570158491720,"updated":1570159749040,"tz":-300,"url":"https://earthquake.usgs.gov/earthquakes/eventpage/us70005qjx","detail":"https://earthquake.usgs.gov/earthquakes/feed/v1.0/detail/us70005qjx.geojson","felt":null,"cdi":null,"mmi":null,"alert":null,"status":"reviewed","tsunami":0,"sig":312,"net":"us","code":"70005qjx","ids":",us70005qjx,","sources":",us,","types":",geoserve,origin,phase-data,","nst":null,"dmin":1.3500000000000001,"rms":1.1899999999999999,"gap":100,"magType":"mwr","type":"earthquake","title":"M 4.5 - 141km WNW of Coquimbo, Chile"},"geometry":{"type":"Point","coordinates":[-72.759200000000007,-29.643899999999999,10]},"id":"us70005qjx"},
{"type":"Feature","properties":{"mag":4.7000000000000002,"place":"63km E of Bitung, Indonesia","time":1570149957701,"updated":1570154216040,"tz":480,"url":"https://earthquake.usgs.gov/earthquakes/eventpage/us70005qj2","detail":"https://earthquake.usgs.gov/earthquakes/feed/v1.0/detail/us70005qj2.geojson","felt":null,"cdi":null,"mmi":null,"alert":null,"status":"reviewed","tsunami":0,"sig":340,"net":"us","code":"70005qj2","ids":",us70005qj2,","sources":",us,","types":",geoserve,origin,phase-data,","nst":null,"dmin":1.7350000000000001,"rms":1.3100000000000001,"gap":81,"magType":"mb","type":"earthquake","title":"M 4.7 - 63km E of Bitung, Indonesia"},"geometry":{"type":"Point","coordinates":[125.74809999999999,1.4040999999999999,51.840000000000003]},"id":"us70005qj2"},
{"type":"Feature","properties":{"mag":4.5,"place":"40km NE of Roshtqal'a, Tajikistan","time":1570140177119,"updated":1570191680411,"tz":300,"url":"https://earthquake.usgs.gov/earthquakes/eventpage/us70005qhc","detail":"https://earthquake.usgs.gov/earthquakes/feed/v1.0/detail/us70005qhc.geojson","felt":1,"cdi":2,"mmi":null,"alert":null,"status":"reviewed","tsunami":0,"sig":312,"net":"us","code":"70005qhc","ids":",us70005qhc,","sources":",us,","types":",dyfi,geoserve,origin,phase-data,","nst":null,"dmin":0.41399999999999998,"rms":0.67000000000000004,"gap":54,"magType":"mb","type":"earthquake","title":"M 4.5 - 40km NE of Roshtqal'a, Tajikistan"},"geometry":{"type":"Point","coordinates":[72.179100000000005,37.496200000000002,195.69999999999999]},"id":"us70005qhc"},
{"type":"Feature","properties":{"mag":4.7000000000000002,"place":"232km W of Abepura, Indonesia","time":1570137145956,"updated":1570155387040,"tz":540,"url":"https://earthquake.usgs.gov/earthquakes/eventpage/us70005qh0","detail":"https://earthquake.usgs.gov/earthquakes/feed/v1.0/detail/us70005qh0.geojson","felt":null,"cdi":null,"mmi":null,"alert":null,"status":"reviewed","tsunami":0,"sig":340,"net":"us","code":"70005qh0","ids":",us70005qh0,","sources":",us,","types":",geoserve,origin,phase-data,","nst":null,"dmin":6.242,"rms":0.76000000000000001,"gap":83,"magType":"mb","type":"earthquake","title":"M 4.7 - 232km W of Abepura, Indonesia"},"geometry":{"type":"Point","coordinates":[138.49719999999999,-2.7787999999999999,25.73]},"id":"us70005qh0"},
{"type":"Feature","properties":{"mag":5.5,"place":"251km W of Abepura, Indonesia","time":1570113189139,"updated":1570199690032,"tz":540,"url":"https://earthquake.usgs.gov/earthquakes/eventpage/us70005q83","detail":"https://earthquake.usgs.gov/earthquakes/feed/v1.0/detail/us70005q83.geojson","felt":null,"cdi":null,"mmi":4.4900000000000002,"alert":"green","status":"reviewed","tsunami":1,"sig":465,"net":"us","code":"70005q83","ids":",us70005q83,","sources":",us,","types":",geoserve,losspager,moment-tensor,origin,phase-data,shakemap,","nst":null,"dmin":6.069,"rms":0.93999999999999995,"gap":37,"magType":"mww","type":"earthquake","title":"M 5.5 - 251km W of Abepura, Indonesia"},"geometry":{"type":"Point","coordinates":[138.3219,-2.7069000000000001,51.469999999999999]},"id":"us70005q83"},
{"type":"Feature","properties":{"mag":4.7999999999999998,"place":"243km ESE of Nikol'skoye, Russia","time":1570096122982,"updated":1570110251040,"tz":660,"url":"https://earthquake.usgs.gov/earthquakes/eventpage/us70005q6b","detail":"https://earthquake.usgs.gov/earthquakes/feed/v1.0/detail/us70005q6b.geojson","felt":null,"cdi":null,"mmi":null,"alert":null,"status":"reviewed","tsunami":0,"sig":354,"net":"us","code":"70005q6b","ids":",us70005q6b,","sources":",us,","types":",geoserve,origin,phase-data,","nst":null,"dmin":3.2029999999999998,"rms":1.01,"gap":99,"magType":"mb","type":"earthquake","title":"M 4.8 - 243km ESE of Nikol'skoye, Russia"},"geometry":{"type":"Point","coordinates":[169.2672,54.106999999999999,10]},"id":"us70005q6b"},
{"type":"Feature","properties":{"mag":4.5,"place":"115km ESE of Pangai, Tonga","time":1570093025203,"updated":1570105275040,"tz":-720,"url":"https://earthquake.usgs.gov/earthquakes/eventpage/us70005q64","detail":"https://earthquake.usgs.gov/earthquakes/feed/v1.0/detail/us70005q64.geojson","felt":null,"cdi":null,"mmi":null,"alert":null,"status":"reviewed","tsunami":0,"sig":312,"net":"us","code":"70005q64","ids":",us70005q64,","sources":",us,","types":",geoserve,origin,phase-data,","nst":null,"dmin":3.4300000000000002,"rms":0.77000000000000002,"gap":45,"magType":"mb","type":"earthquake","title":"M 4.5 - 115km ESE of Pangai, Tonga"},"geometry":{"type":"Point","coordinates":[-173.35220000000001,-20.243500000000001,10]},"id":"us70005q64"},
{"type":"Feature","properties":{"mag":4.7000000000000002,"place":"14km SSE of Pelau, Indonesia","time":1570092079475,"updated":1570095320009,"tz":540,"url":"https://earthquake.usgs.gov/earthquakes/eventpage/us70005q5z","detail":"https://earthquake.usgs.gov/earthquakes/feed/v1.0/detail/us70005q5z.geojson","felt":1,"cdi":4.0999999999999996,"mmi":null,"alert":null,"status":"reviewed","tsunami":0,"sig":340,"net":"us","code":"70005q5z","ids":",us70005q5z,","sources":",us,","types":",dyfi,geoserve,origin,phase-data,","nst":null,"dmin":3.7879999999999998,"rms":0.75,"gap":52,"magType":"mb","type":"earthquake","title":"M 4.7 - 14km SSE of Pelau, Indonesia"},"geometry":{"type":"Point","coordinates":[128.523,-3.6425999999999998,10]},"id":"us70005q5z"},
{"type":"Feature","properties":{"mag":4.9000000000000004,"place":"8km ENE of Imphal, India","time":1570083884009,"updated":1570112125385,"tz":330,"url":"https://earthquake.usgs.gov/earthquakes/eventpage/us70005q55","detail":"https://earthquake.usgs.gov/earthquakes/feed/v1.0/detail/us70005q55.geojson","felt":3,"cdi":3.8999999999999999,"mmi":null,"alert":null,"status":"reviewed","tsunami":0,"sig":371,"net":"us","code":"70005q55","ids":",us70005q55,","sources":",us,","types":",dyfi,geoserve,origin,phase-data,","nst":null,"dmin":0.65300000000000002,"rms":0.70999999999999996,"gap":50,"magType":"mb","type":"earthquake","title":"M 4.9 - 8km ENE of Imphal, India"},"geometry":{"type":"Point","coordinates":[94.033799999999999,24.838899999999999,66.430000000000007]},"id":"us70005q55"},
{"type":"Feature","properties":{"mag":4.5999999999999996,"place":"14km NNW of Wawa, Philippines","time":1570078500810,"updated":1570081017819,"tz":480,"url":"https://earthquake.usgs.gov/earthquakes/eventpage/us70005q4r","detail":"https://earthquake.usgs.gov/earthquakes/feed/v1.0/detail/us70005q4r.geojson","felt":1,"cdi":2,"mmi":null,"alert":null,"status":"reviewed","tsunami":0,"sig":326,"net":"us","code":"70005q4r","ids":",us70005q4r,","sources":",us,","types":",dyfi,geoserve,origin,phase-data,","nst":null,"dmin":8.6359999999999992,"rms":0.83999999999999997,"gap":130,"magType":"mb","type":"earthquake","title":"M 4.6 - 14km NNW of Wawa, Philippines"},"geometry":{"type":"Point","coordinates":[120.70950000000001,13.587400000000001,179.81]},"id":"us70005q4r"},
{"type":"Feature","properties":{"mag":5.0999999999999996,"place":"36km ESE of Faliraki, Greece","time":1570077896951,"updated":1570479171633,"tz":120,"url":"https://earthquake.usgs.gov/earthquakes/eventpage/us70005q4l","detail":"https://earthquake.usgs.gov/earthquakes/feed/v1.0/detail/us70005q4l.geojson","felt":236,"cdi":4.2999999999999998,"mmi":null,"alert":null,"status":"reviewed","tsunami":0,"sig":502,"net":"us","code":"70005q4l","ids":",us70005q4l,","sources":",us,","types":",dyfi,geoserve,moment-tensor,origin,phase-data,","nst":null,"dmin":0.379,"rms":1.24,"gap":42,"magType":"mww","type":"earthquake","title":"M 5.1 - 36km ESE of Faliraki, Greece"},"geometry":{"type":"Point","coordinates":[28.587499999999999,36.256799999999998,18.710000000000001]},"id":"us70005q4l"},
{"type":"Feature","properties":{"mag":4.7000000000000002,"place":"128km ENE of Miyako, Japan","time":1570074946732,"updated":1570075868040,"tz":600,"url":"https://earthquake.usgs.gov/earthquakes/eventpage/us70005q4d","detail":"https://earthquake.usgs.gov/earthquakes/feed/v1.0/detail/us70005q4d.geojson","felt":null,"cdi":null,"mmi":null,"alert":null,"status":"reviewed","tsunami":0,"sig":340,"net":"us","code":"70005q4d","ids":",us70005q4d,","sources":",us,","types":",geoserve,origin,phase-data,","nst":null,"dmin":2.032,"rms":0.85999999999999999,"gap":102,"magType":"mb","type":"earthquake","title":"M 4.7 - 128km ENE of Miyako, Japan"},"geometry":{"type":"Point","coordinates":[143.4239,39.852400000000003,35]},"id":"us70005q4d"},
{"type":"Feature","properties":{"mag":4.9000000000000004,"place":"53km NNW of Visokoi Island, South Georgia and the South Sandwich Islands","time":1570067710069,"updated":1570070424040,"tz":-120,"url":"https://earthquake.usgs.gov/earthquakes/eventpage/us70005q41","detail":"https://earthquake.usgs.gov/earthquakes/feed/v1.0/detail/us70005q41.geojson","felt":null,"cdi":null,"mmi":null,"alert":null,"status":"reviewed","tsunami":0,"sig":369,"net":"us","code":"70005q41","ids":",us70005q41,","sources":",us,","types":",geoserve,origin,phase-data,","nst":null,"dmin":5.4870000000000001,"rms":0.77000000000000002,"gap":80,"magType":"mb","type":"earthquake","title":"M 4.9 - 53km NNW of Visokoi Island, South Georgia and the South Sandwich Islands"},"geometry":{"type":"Point","coordinates":[-27.531099999999999,-56.252299999999998,121.03]},"id":"us70005q41"},
{"type":"Feature","properties":{"mag":5.0999999999999996,"place":"205km WSW of Visokoi Island, South Georgia and the South Sandwich Islands","time":1570065103613,"updated":1570066482040,"tz":-120,"url":"https://earthquake.usgs.gov/earthquakes/eventpage/us70005q3b","detail":"https://earthquake.usgs.gov/earthquakes/feed/v1.0/detail/us70005q3b.geojson","felt":null,"cdi":null,"mmi":null,"alert":null,"status":"reviewed","tsunami":0,"sig":400,"net":"us","code":"70005q3b","ids":",us70005q3b,","sources":",us,","types":",geoserve,origin,phase-data,","nst":null,"dmin":4.3579999999999997,"rms":0.62,"gap":75,"magType":"mb","type":"earthquake","title":"M 5.1 - 205km WSW of Visokoi Island, South Georgia and the South Sandwich Islands"},"geometry":{"type":"Point","coordinates":[-30.511600000000001,-57.024099999999997,10]},"id":"us70005q3b"},
{"type":"Feature","properties":{"mag":4.5,"place":"60km SE of Ozernovskiy, Russia","time":1570063165662,"updated":1570078177040,"tz":720,"url":"https://earthquake.usgs.gov/earthquakes/eventpage/us70005q33","detail":"https://earthquake.usgs.gov/earthquakes/feed/v1.0/detail/us70005q33.geojson","felt":null,"cdi":null,"mmi":null,"alert":null,"status":"reviewed","tsunami":0,"sig":312,"net":"us","code":"70005q33","ids":",us70005q33,","sources":",us,","types":",geoserve,origin,phase-data,","nst":null,"dmin":2.069,"rms":0.41999999999999998,"gap":162,"magType":"mb","type":"earthquake","title":"M 4.5 - 60km SE of Ozernovskiy, Russia"},"geometry":{"type":"Point","coordinates":[157.05760000000001,51.080300000000001,85.680000000000007]},"id":"us70005q33"},
{"type":"Feature","properties":{"mag":4.5,"place":"7km NW of Sechura, Peru","time":1570052580925,"updated":1570105318602,"tz":-300,"url":"https://earthquake.usgs.gov/earthquakes/eventpage/us70005q1k","detail":"https://earthquake.usgs.gov/earthquakes/feed/v1.0/detail/us70005q1k.geojson","felt":2,"cdi":4.2999999999999998,"mmi":null,"alert":null,"status":"reviewed","tsunami":0,"sig":312,"net":"us","code":"70005q1k","ids":",us70005q1k,","sources":",us,","types":",dyfi,geoserve,origin,phase-data,","nst":null,"dmin":3.4300000000000002,"rms":0.68000000000000005,"gap":148,"magType":"mb","type":"earthquake","title":"M 4.5 - 7km NW of Sechura, Peru"},"geometry":{"type":"Point","coordinates":[-80.875500000000002,-5.5128000000000004,35]},"id":"us70005q1k"},
{"type":"Feature","properties":{"mag":4.5999999999999996,"place":"76km SW of Banda Aceh, Indonesia","time":1570052299935,"updated":1570055056040,"tz":360,"url":"https://earthquake.usgs.gov/earthquakes/eventpage/us70005q1u","detail":"https://earthquake.usgs.gov/earthquakes/feed/v1.0/detail/us70005q1u.geojson","felt":null,"cdi":null,"mmi":null,"alert":null,"status":"reviewed","tsunami":0,"sig":326,"net":"us","code":"70005q1u","ids":",us70005q1u,","sources":",us,","types":",geoserve,origin,phase-data,","nst":null,"dmin":2.1600000000000001,"rms":0.56999999999999995,"gap":136,"magType":"mb","type":"earthquake","title":"M 4.6 - 76km SW of Banda Aceh, Indonesia"},"geometry":{"type":"Point","coordinates":[94.780100000000004,5.1269,69.319999999999993]},"id":"us70005q1u"},
{"type":"Feature","properties":{"mag":4.5999999999999996,"place":"132km NE of Agrihan, Northern Mariana Islands","time":1570047054393,"updated":1570052456040,"tz":600,"url":"https://earthquake.usgs.gov/earthquakes/eventpage/us70005pzy","detail":"https://earthquake.usgs.gov/earthquakes/feed/v1.0/detail/us70005pzy.geojson","felt":null,"cdi":null,"mmi":null,"alert":null,"status":"reviewed","tsunami":0,"sig":326,"net":"us","code":"70005pzy","ids":",us70005pzy,","sources":",us,","types":",geoserve,origin,phase-data,","nst":null,"dmin":4.5229999999999997,"rms":1.02,"gap":125,"magType":"mb","type":"earthquake","title":"M 4.6 - 132km NE of Agrihan, Northern Mariana Islands"},"geometry":{"type":"Point","coordinates":[146.37569999999999,19.754300000000001,72.040000000000006]},"id":"us70005pzy"},
{"type":"Feature","properties":{"mag":4.7999999999999998,"place":"81km SE of San Pedro de Atacama, Chile","time":1570037210995,"updated":1570052154040,"tz":-240,"url":"https://earthquake.usgs.gov/earthquakes/eventpage/us70005pvy","detail":"https://earthquake.usgs.gov/earthquakes/feed/v1.0/detail/us70005pvy.geojson","felt":null,"cdi":null,"mmi":null,"alert":null,"status":"reviewed","tsunami":0,"sig":354,"net":"us","code":"70005pvy","ids":",us70005pvy,","sources":",us,","types":",geoserve,moment-tensor,origin,phase-data,","nst":null,"dmin":0.68200000000000005,"rms":1.1599999999999999,"gap":46,"magType":"mww","type":"earthquake","title":"M 4.8 - 81km SE of San Pedro de Atacama, Chile"},"geometry":{"type":"Point","coordinates":[-67.624799999999993,-23.407299999999999,131.49000000000001]},"id":"us70005pvy"},
{"type":"Feature","properties":{"mag":4.5,"place":"124km SSE of Hachijo-jima, Japan","time":1570028329149,"updated":1570081498040,"tz":540,"url":"https://earthquake.usgs.gov/earthquakes/eventpage/us70005ptl","detail":"https://earthquake.usgs.gov/earthquakes/feed/v1.0/detail/us70005ptl.geojson","felt":null,"cdi":null,"mmi":null,"alert":null,"status":"reviewed","tsunami":0,"sig":312,"net":"us","code":"70005ptl","ids":",us70005ptl,","sources":",us,","types":",geoserve,origin,phase-data,","nst":null,"dmin":1.1439999999999999,"rms":0.95999999999999996,"gap":152,"magType":"mb","type":"earthquake","title":"M 4.5 - 124km SSE of Hachijo-jima, Japan"},"geometry":{"type":"Point","coordinates":[140.35400000000001,32.062199999999997,90.980000000000004]},"id":"us70005ptl"},
{"type":"Feature","properties":{"mag":5.0999999999999996,"place":"196km W of Abepura, Indonesia","time":1570026271425,"updated":1570028987040,"tz":540,"url":"https://earthquake.usgs.gov/earthquakes/eventpage/us70005pt7","detail":"https://earthquake.usgs.gov/earthquakes/feed/v1.0/detail/us70005pt7.geojson","felt":null,"cdi":null,"mmi":null,"alert":null,"status":"reviewed","tsunami":1,"sig":400,"net":"us","code":"70005pt7","ids":",us70005pt7,","sources":",us,","types":",geoserve,origin,phase-data,","nst":null,"dmin":6.5670000000000002,"rms":0.57999999999999996,"gap":58,"magType":"mb","type":"earthquake","title":"M 5.1 - 196km W of Abepura, Indonesia"},"geometry":{"type":"Point","coordinates":[138.8194,-2.6655000000000002,35]},"id":"us70005pt7"},
{"type":"Feature","properties":{"mag":4.5,"place":"0km S of Lucsuhin, Philippines","time":1570024402164,"updated":1570051529932,"tz":480,"url":"https://earthquake.usgs.gov/earthquakes/eventpage/us70005pt0","detail":"https://earthquake.usgs.gov/earthquakes/feed/v1.0/detail/us70005pt0.geojson","felt":1,"cdi":2.7000000000000002,"mmi":null,"alert":null,"status":"reviewed","tsunami":0,"sig":312,"net":"us","code":"70005pt0","ids":",us70005pt0,","sources":",us,","types":",dyfi,geoserve,origin,phase-data,","nst":null,"dmin":8.3290000000000006,"rms":0.5,"gap":114,"magType":"mb","type":"earthquake","title":"M 4.5 - 0km S of Lucsuhin, Philippines"},"geometry":{"type":"Point","coordinates":[120.6412,13.881,69.430000000000007]},"id":"us70005pt0"},
{"type":"Feature","properties":{"mag":4.5,"place":"233km E of Amahai, Indonesia","time":1570020869921,"updated":1570080720040,"tz":540,"url":"https://earthquake.usgs.gov/earthquakes/eventpage/us70005psm","detail":"https://earthquake.usgs.gov/earthquakes/feed/v1.0/detail/us70005psm.geojson","felt":null,"cdi":null,"mmi":null,"alert":null,"status":"reviewed","tsunami":0,"sig":312,"net":"us","code":"70005psm","ids":",us70005psm,","sources":",us,","types":",geoserve,origin,phase-data,","nst":null,"dmin":1.3600000000000001,"rms":0.81999999999999995,"gap":89,"magType":"mb","type":"earthquake","title":"M 4.5 - 233km E of Amahai, Indonesia"},"geometry":{"type":"Point","coordinates":[131.00919999999999,-3.4868999999999999,10]},"id":"us70005psm"},
{"type":"Feature","properties":{"mag":4.5999999999999996,"place":"3km SE of Corredor, Costa Rica","time":1570020774763,"updated":1570513966454,"tz":-360,"url":"https://earthquake.usgs.gov/earthquakes/eventpage/us70005psl","detail":"https://earthquake.usgs.gov/earthquakes/feed/v1.0/detail/us70005psl.geojson","felt":1,"cdi":4.2000000000000002,"mmi":null,"alert":null,"status":"reviewed","tsunami":0,"sig":326,"net":"us","code":"70005psl","ids":",us70005psl,","sources":",us,","types":",dyfi,geoserve,origin,phase-data,","nst":null,"dmin":0.29299999999999998,"rms":0.83999999999999997,"gap":81,"magType":"mb","type":"earthquake","title":"M 4.6 - 3km SE of Corredor, Costa Rica"},"geometry":{"type":"Point","coordinates":[-82.926500000000004,8.6182999999999996,11.130000000000001]},"id":"us70005psl"},
{"type":"Feature","properties":{"mag":5,"place":"66km NNE of Xujiaba, China","time":1570017875235,"updated":1570029299040,"tz":480,"url":"https://earthquake.usgs.gov/earthquakes/eventpage/us70005psh","detail":"https://earthquake.usgs.gov/earthquakes/feed/v1.0/detail/us70005psh.geojson","felt":null,"cdi":null,"mmi":null,"alert":null,"status":"reviewed","tsunami":0,"sig":385,"net":"us","code":"70005psh","ids":",us70005psh,","sources":",us,","types":",geoserve,moment-tensor,origin,phase-data,","nst":null,"dmin":8.0380000000000003,"rms":0.75,"gap":34,"magType":"mb","type":"earthquake","title":"M 5.0 - 66km NNE of Xujiaba, China"},"geometry":{"type":"Point","coordinates":[108.3887,28.434000000000001,10]},"id":"us70005psh"},
{"type":"Feature","properties":{"mag":4.7000000000000002,"place":"Carlsberg Ridge","time":1570012195498,"updated":1570013184040,"tz":240,"url":"https://earthquake.usgs.gov/earthquakes/eventpage/us70005prz","detail":"https://earthquake.usgs.gov/earthquakes/feed/v1.0/detail/us70005prz.geojson","felt":null,"cdi":null,"mmi":null,"alert":null,"status":"reviewed","tsunami":0,"sig":340,"net":"us","code":"70005prz","ids":",us70005prz,","sources":",us,","types":",geoserve,origin,phase-data,","nst":null,"dmin":11.85,"rms":0.60999999999999999,"gap":111,"magType":"mb","type":"earthquake","title":"M 4.7 - Carlsberg Ridge"},"geometry":{"type":"Point","coordinates":[64.104699999999994,3.5137999999999998,10]},"id":"us70005prz"},
{"type":"Feature","properties":{"mag":5.2000000000000002,"place":"39km S of San Mateo del Mar, Mexico","time":1570011191476,"updated":1570033812184,"tz":-360,"url":"https://earthquake.usgs.gov/earthquakes/eventpage/us70005prt","detail":"https://earthquake.usgs.gov/earthquakes/feed/v1.0/detail/us70005prt.geojson","felt":10,"cdi":4.5999999999999996,"mmi":null,"alert":null,"status":"reviewed","tsunami":0,"sig":421,"net":"us","code":"70005prt","ids":",us70005prt,","sources":",us,","types":",dyfi,geoserve,moment-tensor,origin,phase-data,","nst":null,"dmin":2.742,"rms":0.93000000000000005,"gap":138,"magType":"mww","type":"earthquake","title":"M 5.2 - 39km S of San Mateo del Mar, Mexico"},"geometry":{"type":"Point","coordinates":[-94.953299999999999,15.844799999999999,44.130000000000003]},"id":"us70005prt"},
{"type":"Feature","properties":{"mag":4.7000000000000002,"place":"147km W of Coquimbo, Chile","time":1570000270116,"updated":1570003418040,"tz":-300,"url":"https://earthquake.usgs.gov/earthquakes/eventpage/us70005pq8","detail":"https://earthquake.usgs.gov/earthquakes/feed/v1.0/detail/us70005pq8.geojson","felt":null,"cdi":null,"mmi":null,"alert":null,"status":"reviewed","tsunami":0,"sig":340,"net":"us","code":"70005pq8","ids":",us70005pq8,","sources":",us,","types":",geoserve,origin,phase-data,","nst":null,"dmin":1.4059999999999999,"rms":1.3200000000000001,"gap":100,"magType":"mb","type":"earthquake","title":"M 4.7 - 147km W of Coquimbo, Chile"},"geometry":{"type":"Point","coordinates":[-72.840299999999999,-29.715800000000002,10]},"id":"us70005pq8"}],"bbox":[-177.8679,-61.0738,6.4,178.1003,62.4784,571.71]}